[
    {
        "phoneme": "",
        "start_time": 0.0,
        "end_time": 0.03,
        "duration": 0.03
    },
    {
        "phoneme": "z̪",
        "start_time": 0.03,
        "end_time": 0.14,
        "duration": 0.11000000000000001
    },
    {
        "phoneme": "ɑ",
        "start_time": 0.14,
        "end_time": 0.26,
        "duration": 0.12
    },
    {
        "phoneme": "ʋ",
        "start_time": 0.26,
        "end_time": 0.32,
        "duration": 0.06
    },
    {
        "phoneme": "t̪",
        "start_time": 0.32,
        "end_time": 0.39,
        "duration": 0.07
    },
    {
        "phoneme": "ɾ",
        "start_time": 0.39,
        "end_time": 0.44,
        "duration": 0.04999999999999999
    },
    {
        "phoneme": "ɐ",
        "start_time": 0.44,
        "end_time": 0.55,
        "duration": 0.11000000000000004
    },
    {
        "phoneme": "z̪",
        "start_time": 0.55,
        "end_time": 0.62,
        "duration": 0.06999999999999995
    },
    {
        "phoneme": "ɑ",
        "start_time": 0.62,
        "end_time": 0.75,
        "duration": 0.13
    },
    {
        "phoneme": "ɾ",
        "start_time": 0.75,
        "end_time": 0.79,
        "duration": 0.040000000000000036
    },
    {
        "phoneme": "ɐ",
        "start_time": 0.79,
        "end_time": 0.86,
        "duration": 0.06999999999999995
    },
    {
        "phoneme": "z̪",
        "start_time": 0.86,
        "end_time": 0.94,
        "duration": 0.07999999999999996
    },
    {
        "phoneme": "k",
        "start_time": 0.94,
        "end_time": 1.02,
        "duration": 0.08000000000000007
    },
    {
        "phoneme": "ɔ",
        "start_time": 1.02,
        "end_time": 1.07,
        "duration": 0.050000000000000044
    },
    {
        "phoneme": "l",
        "start_time": 1.07,
        "end_time": 1.14,
        "duration": 0.06999999999999984
    },
    {
        "phoneme": "ɪ",
        "start_time": 1.14,
        "end_time": 1.17,
        "duration": 0.030000000000000027
    },
    {
        "phoneme": "ʋ",
        "start_time": 1.17,
        "end_time": 1.22,
        "duration": 0.050000000000000044
    },
    {
        "phoneme": "ɪ",
        "start_time": 1.22,
        "end_time": 1.25,
        "duration": 0.030000000000000027
    },
    {
        "phoneme": "spn",
        "start_time": 1.25,
        "end_time": 2.06,
        "duration": 0.81
    },
    {
        "phoneme": "",
        "start_time": 2.06,
        "end_time": 2.09002,
        "duration": 0.030019999999999936
    }
]